kast_flow_api/__init__.py
kast_flow_api/v1.py
kast_flow_api_python-1.0.9.dist-info/METADATA
kast_flow_api_python-1.0.9.dist-info/WHEEL
kast_flow_api_python-1.0.9.dist-info/RECORD
